odoo/addons/partner_time_to_pay/README.rst
odoo/addons/partner_time_to_pay/__init__.py
odoo/addons/partner_time_to_pay/__manifest__.py
odoo/addons/partner_time_to_pay/i18n/ca.po
odoo/addons/partner_time_to_pay/i18n/es.po
odoo/addons/partner_time_to_pay/i18n/fr.po
odoo/addons/partner_time_to_pay/i18n/it.po
odoo/addons/partner_time_to_pay/i18n/nl_NL.po
odoo/addons/partner_time_to_pay/i18n/partner_time_to_pay.pot
odoo/addons/partner_time_to_pay/i18n/pt.po
odoo/addons/partner_time_to_pay/models/__init__.py
odoo/addons/partner_time_to_pay/models/account_move.py
odoo/addons/partner_time_to_pay/models/res_partner.py
odoo/addons/partner_time_to_pay/readme/CONTRIBUTORS.md
odoo/addons/partner_time_to_pay/readme/CREDITS.md
odoo/addons/partner_time_to_pay/readme/DESCRIPTION.md
odoo/addons/partner_time_to_pay/readme/INSTALL.md
odoo/addons/partner_time_to_pay/readme/ROADMAP.md
odoo/addons/partner_time_to_pay/readme/USAGE.md
odoo/addons/partner_time_to_pay/static/description/icon.png
odoo/addons/partner_time_to_pay/static/description/index.html
odoo/addons/partner_time_to_pay/tests/__init__.py
odoo/addons/partner_time_to_pay/tests/test_partner_time_to_pay.py
odoo/addons/partner_time_to_pay/views/account_move_view.xml
odoo/addons/partner_time_to_pay/views/res_partner_view.xml
odoo_addon_partner_time_to_pay-17.0.1.0.0.3.dist-info/METADATA
odoo_addon_partner_time_to_pay-17.0.1.0.0.3.dist-info/WHEEL
odoo_addon_partner_time_to_pay-17.0.1.0.0.3.dist-info/top_level.txt
odoo_addon_partner_time_to_pay-17.0.1.0.0.3.dist-info/RECORD
