Metadata-Version: 2.1
Name: odoo-addon-partner_time_to_pay
Version: 17.0.1.0.0.3
Requires-Python: >=3.10
Requires-Dist: odoo>=17.0a,<17.1dev
Summary: Add receivables and payables statistics to partners
Home-page: https://github.com/OCA/account-invoice-reporting
License: AGPL-3
Author: Open Source Integrators, Odoo Community Association (OCA), Moduon
Author-email: support@odoo-community.org
Classifier: Programming Language :: Python
Classifier: Framework :: Odoo
Classifier: Framework :: Odoo :: 17.0
Classifier: License :: OSI Approved :: GNU Affero General Public License v3
Classifier: Development Status :: 4 - Beta
